gazouilloire/__init__.py
gazouilloire/__version__.py
gazouilloire/api_wrapper.py
gazouilloire/config.json.example
gazouilloire/config_format.py
gazouilloire/daemon.py
gazouilloire/manage_scripts.py
gazouilloire/multiprocessing.py
gazouilloire/resolving_script.py
gazouilloire/run.py
gazouilloire/test_metas.py
gazouilloire/test_search.py
gazouilloire/test_stream.py
gazouilloire/twitter_connexion.py
gazouilloire/url_resolve.py
gazouilloire/cli/__init__.py
gazouilloire/cli/__main__.py
gazouilloire/database/__init__.py
gazouilloire/database/db_mappings.json
gazouilloire/database/elasticmanager.py
gazouilloire/exports/__init__.py
gazouilloire/exports/export.py
gazouilloire/exports/tweet_fields.py
gazouilloire/scripts/add_bearer_token_to_conf.sh
gazouilloire/scripts/backup_corpus_ids.sh
gazouilloire/scripts/daily_mail_export.sh
gazouilloire/scripts/elasticdump.sh
gazouilloire/scripts/monthly_archive.sh
gazouilloire/scripts/restart.sh
gazouilloire/web/__init__.py
gazouilloire/web/app.py
gazouilloire/web/export.py
gazouilloire-1.5.0.dist-info/LICENSE
gazouilloire-1.5.0.dist-info/METADATA
gazouilloire-1.5.0.dist-info/WHEEL
gazouilloire-1.5.0.dist-info/entry_points.txt
gazouilloire-1.5.0.dist-info/top_level.txt
gazouilloire-1.5.0.dist-info/RECORD
