Metadata-Version: 2.1
Name: gazouilloire
Version: 1.5.0
Summary: Twitter stream & search API grabber
Home-page: http://github.com/medialab/gazouilloire
Author: Benjamin Ooghe-Tabanou
Author-email: 
License: GPL-3.0
Keywords: twitter
Requires-Python: >=3.7
License-File: LICENSE
Requires-Dist: elasticsearch (<8.0,>=7.10.1)
Requires-Dist: requests
Requires-Dist: psutil
Requires-Dist: minet (>=0.63.1)
Requires-Dist: future
Requires-Dist: click
Requires-Dist: tqdm
